charz_core/__init__.py
charz_core/_camera.py
charz_core/_components/transform.py
charz_core/_engine.py
charz_core/_frame_task.py
charz_core/_grouping.py
charz_core/_node.py
charz_core/_prefabs/node2d.py
charz_core/_scene.py
charz_core/py.typed
charz_core/typing.py
charz_core-0.1.4.dist-info/WHEEL
charz_core-0.1.4.dist-info/METADATA
charz_core-0.1.4.dist-info/RECORD
